_mt2/lester_mt2_bisect_v7.h
_mt2/main.cpp
_mt2/mt2_Lallyver2.h
_mt2/mt2_bisect.h
mt2/__init__.py
mt2/_mt2.cp311-win_arm64.pyd
mt2/diagnostics.py
mt2-1.3.1.dist-info/licenses/LICENSE
mt2-1.3.1.dist-info/METADATA
mt2-1.3.1.dist-info/WHEEL
mt2-1.3.1.dist-info/top_level.txt
mt2-1.3.1.dist-info/RECORD
