Metadata-Version: 2.4
Name: mt2
Version: 1.3.1
Summary: Stransverse mass computation as a numpy ufunc.
Author: Rupert Tombs, Christopher Lester
Author-email: Tom Gillam <tpgillam@googlemail.com>
License-Expression: MIT
Project-URL: Homepage, https://github.com/tpgillam/mt2
Keywords: mt2
Classifier: Development Status :: 5 - Production/Stable
Classifier: Intended Audience :: Developers
Classifier: Natural Language :: English
Classifier: Programming Language :: Python :: 3
Classifier: Programming Language :: Python :: 3.9
Classifier: Programming Language :: Python :: 3.10
Classifier: Programming Language :: Python :: 3.11
Classifier: Programming Language :: Python :: 3.12
Classifier: Programming Language :: Python :: 3.13
Classifier: Programming Language :: Python :: 3.14
Requires-Python: >=3.9
License-File: LICENSE
Requires-Dist: numpy>=1.19.3
Dynamic: license-file
